pocketwalk/__init__.py
pocketwalk/core.py
pocketwalk/plugger.py
pocketwalk/plugins/__init__.py
pocketwalk/plugins/cancellation.py
pocketwalk/plugins/config.py
pocketwalk/plugins/context_manager.py
pocketwalk/plugins/tool_runner.py
pocketwalk/plugins/vcs.py
pocketwalk/shell/__init__.py
pocketwalk/shell/cancellation.py
pocketwalk/shell/config.py
pocketwalk/shell/context_manager.py
pocketwalk/shell/tool_runner.py
pocketwalk/shell/vcs.py
pocketwalk-0.2.2.dist-info/DESCRIPTION.rst
pocketwalk-0.2.2.dist-info/METADATA
pocketwalk-0.2.2.dist-info/RECORD
pocketwalk-0.2.2.dist-info/WHEEL
pocketwalk-0.2.2.dist-info/entry_points.txt
pocketwalk-0.2.2.dist-info/metadata.json
pocketwalk-0.2.2.dist-info/top_level.txt
