Metadata-Version: 2.0
Name: pocketwalk
Version: 0.2.2
Summary: Pocketwalk: Watch/Run/Commit.
Home-page: https://github.com/toejough/pocketwalk
Author: toejough
Author-email: toejough@gmail.com
License: UNKNOWN
Keywords: watch run commit
Platform: UNKNOWN
Classifier: Development Status :: 3 - Alpha
Classifier: Intended Audience :: Developers
Classifier: License :: OSI Approved :: Apache Software License
Classifier: Programming Language :: Python :: 3
Classifier: Programming Language :: Python :: 3.6
Requires-Dist: pytoml
Requires-Dist: runaway (==0.2.1)
Requires-Dist: wrapt
Provides-Extra: checkers
Requires-Dist: dodgy; extra == 'checkers'
Requires-Dist: flake8; extra == 'checkers'
Requires-Dist: flake8-blind-except; extra == 'checkers'
Requires-Dist: flake8-bugbear; extra == 'checkers'
Requires-Dist: flake8-builtins; extra == 'checkers'
Requires-Dist: flake8-coding; extra == 'checkers'
Requires-Dist: flake8-commas; extra == 'checkers'
Requires-Dist: flake8-comprehensions; extra == 'checkers'
Requires-Dist: flake8-debugger; extra == 'checkers'
Requires-Dist: flake8-deprecated; extra == 'checkers'
Requires-Dist: flake8-docstrings; extra == 'checkers'
Requires-Dist: flake8-import-order; extra == 'checkers'
Requires-Dist: flake8-mutable; extra == 'checkers'
Requires-Dist: flake8-quotes; extra == 'checkers'
Requires-Dist: flake8-string-format; extra == 'checkers'
Requires-Dist: flake8-tidy-imports; extra == 'checkers'
Requires-Dist: flake8-todo; extra == 'checkers'
Requires-Dist: flake8-tuple; extra == 'checkers'
Requires-Dist: mccabe; extra == 'checkers'
Requires-Dist: mypy; extra == 'checkers'
Requires-Dist: pep8-naming; extra == 'checkers'
Requires-Dist: pylint; extra == 'checkers'
Requires-Dist: vulture; extra == 'checkers'
Provides-Extra: testing
Requires-Dist: dado; extra == 'testing'
Requires-Dist: pytest; extra == 'testing'
